setup.py
Raitonoberu/__init__.py
Raitonoberu/raitonoberu.py
Raitonoberu.egg-info/PKG-INFO
Raitonoberu.egg-info/SOURCES.txt
Raitonoberu.egg-info/dependency_links.txt
Raitonoberu.egg-info/requires.txt
Raitonoberu.egg-info/top_level.txt